bomber/__init__.py
bomber/bomber.py
haxorsiambomber-1.1.3.dist-info/LICENSE
haxorsiambomber-1.1.3.dist-info/METADATA
haxorsiambomber-1.1.3.dist-info/WHEEL
haxorsiambomber-1.1.3.dist-info/top_level.txt
haxorsiambomber-1.1.3.dist-info/RECORD
