Metadata-Version: 2.1
Name: haxorsiambomber
Version: 1.1.3
Summary: SMS Bomber Project.
Home-page: https://github.com/Aru-Ofc-git/ARU-BOMBER.git
Author: SIAM RAHMAN
Author-email: arifulislamarman02@gmail.com
Project-URL: Bug Tracker, https://github.com/SIAMRAHMAN000
Classifier: Development Status :: 5 - Production/Stable
Classifier: Programming Language :: Python :: 3
Classifier: Programming Language :: Python :: 3.5
Classifier: Programming Language :: Python
Classifier: License :: OSI Approved :: MIT License
Classifier: Operating System :: OS Independent
Requires-Python: >=3.6
License-File: LICENSE
